lightning_ddp/__init__.py
lightning_ddp/ddp_env_intializer.py
lightning_ddp/test.py
deeplearning_lib-1.1.dist-info/LICENSE.txt
deeplearning_lib-1.1.dist-info/METADATA
deeplearning_lib-1.1.dist-info/WHEEL
deeplearning_lib-1.1.dist-info/top_level.txt
deeplearning_lib-1.1.dist-info/RECORD
